rspyai-0.1.1.dist-info/METADATA
rspyai-0.1.1.dist-info/WHEEL
rspyai-0.1.1.dist-info/entry_points.txt
rspyai/models/function_summary.py
rspyai/tui.py
rspyai/__init__.py
rspyai/logging.py
rspyai/settings.py
rspyai/widgets/function_summary.py
rspyai/widgets/function_details.py
rspyai/widgets/function_tree.py
rspyai/rspyai.pyi
rspyai/rspyai.cpython-312-i386-linux-gnu.so
rspyai-0.1.1.dist-info/RECORD
