Metadata-Version: 2.4
Name: rspyai
Version: 0.1.1
Classifier: Programming Language :: Rust
Classifier: Programming Language :: Python :: Implementation :: CPython
Classifier: Programming Language :: Python :: Implementation :: PyPy
Requires-Dist: pydantic-ai-slim[openai]
Requires-Dist: pydantic-settings
Requires-Dist: textual
Requires-Dist: pip ; extra == 'dev'
Requires-Dist: ruff ; extra == 'dev'
Requires-Dist: pyright ; extra == 'dev'
Requires-Dist: ipython ; extra == 'dev'
Requires-Dist: maturin ; extra == 'dev'
Requires-Dist: pre-commit ; extra == 'dev'
Provides-Extra: dev
Requires-Python: >=3.12
Project-URL: Homepage, https://github.com/zzstoatzz/rspyai
Project-URL: Source, https://github.com/zzstoatzz/rspyai
Project-URL: Readme, https://github.com/zzstoatzz/rspyai/blob/main/README.md
